README.txt
setup.cfg
setup.py
docs/HISTORY.txt
docs/LICENSE.GPL
docs/LICENSE.txt
raptus/__init__.py
raptus.torii.ipython.egg-info/PKG-INFO
raptus.torii.ipython.egg-info/SOURCES.txt
raptus.torii.ipython.egg-info/dependency_links.txt
raptus.torii.ipython.egg-info/entry_points.txt
raptus.torii.ipython.egg-info/namespace_packages.txt
raptus.torii.ipython.egg-info/not-zip-safe
raptus.torii.ipython.egg-info/requires.txt
raptus.torii.ipython.egg-info/top_level.txt
raptus/torii/__init__.py
raptus/torii/ipython/__init__.py
raptus/torii/ipython/ipython.py